{"stats":{"minecraft:killed":{"minecraft:silverfish":3,"enemyexpansion:drone":4},"minecraft:killed_by":{"enemyexpansion:drone":5,"minecraft:husk":1,"enemyexpansion:vampflyer":1},"minecraft:used":{"enemyexpansion:silverhead_helmet":4,"enemyexpansion:vampire_spawn_egg":1,"minecraft:rotten_flesh":1},"minecraft:dropped":{"minecraft:rotten_flesh":1,"minecraft:arrow":1},"minecraft:custom":{"minecraft:open_chest":1,"minecraft:time_since_rest":3972,"minecraft:crouch_one_cm":2388,"minecraft:damage_taken":2655,"minecraft:play_time":25474,"minecraft:sprint_one_cm":82605,"minecraft:deaths":10,"minecraft:walk_one_cm":73796,"minecraft:sneak_time":1534,"minecraft:walk_under_water_one_cm":1363,"minecraft:mob_kills":31,"minecraft:drop":2,"minecraft:jump":276,"minecraft:damage_dealt":713,"minecraft:leave_game":9,"minecraft:time_since_death":3537,"minecraft:walk_on_water_one_cm":3914,"minecraft:total_world_time":27261,"minecraft:swim_one_cm":1100,"minecraft:fall_one_cm":17658,"minecraft:fly_one_cm":474289},"minecraft:picked_up":{"enemyexpansion:silverhead_helmet":3,"minecraft:arrow":1,"minecraft:rotten_flesh":2,"enemyexpansion:wasp_thorax":54}},"DataVersion":3120}